{
  "adrenalin": {
    "figures": 0,
    "answer": [
      "그래 .. 거절할 줄 알았어",
      "그럴 수도 있지 뭐"
    ]
  },
  "cortisol": {
    "figures": 1,
    "answer": [
      "그래... 알겠어...",
      "싫은거구나.. 알겠어."
    ]
  },
  "dopamine": {
    "figures": 0,
    "answer": [
      "헤헤 그럴 수도 있지 뭐",
      "그래 알았어 헤헤"
    ]
  },
  "endorphin": {
    "figures": 0,
    "answer": [
      "그렇구나. 그럴 수도 있지 뭐.. 알았어!",
      "헤헤. 그래 알겠어"
    ]
  },
  "noradrenalin": {
    "figures": 0,
    "answer": [
      "쳇.. 알았어",
      "칫.. 그래"
    ]
  },
  "serotonin": {
    "figures": 0,
    "answer": [
      "알았어. 괜찮아",
      "그래 알았어."
    ]
  }
}